README.md
setup.cfg
setup.py
nodetasks/__init__.py
nodetasks/nodetasks.py
nodetasks.egg-info/PKG-INFO
nodetasks.egg-info/SOURCES.txt
nodetasks.egg-info/dependency_links.txt
nodetasks.egg-info/entry_points.txt
nodetasks.egg-info/requires.txt
nodetasks.egg-info/top_level.txt