Metadata-Version: 2.1
Name: nodetasks
Version: 0.0.7
Summary: Simple CLI script for listing and running npm tasks
Home-page: https://github.com/michalStarski/nodetasks
Author: Michał Starski
Author-email: michal.starski@pm.me
License: MIT
Platform: UNKNOWN
Classifier: Programming Language :: Python :: 3
Requires-Python: >=3.6
